BayesianOptimization/__init__.py
BayesianOptimization-0.0.0.dist-info/LICENSE.txt
BayesianOptimization-0.0.0.dist-info/METADATA
BayesianOptimization-0.0.0.dist-info/WHEEL
BayesianOptimization-0.0.0.dist-info/top_level.txt
BayesianOptimization-0.0.0.dist-info/RECORD
