Metadata-Version: 1.0
Name: BayesianOptimization
Version: 0.0.0
Summary: Bayesian Optimization
Home-page: UNKNOWN
Author: Logan Grado
Author-email: grado.logan@gmail.com
License: UNKNOWN
Platform: UNKNOWN
